{
  "source_format": "pdf",
  "language": "en",
  "full_text_len": 14877,
  "page_count": 9,
  "impact_level": 2,
  "current_score": 43,
  "raw_impact_score": 43,
  "mitigation_score": 31,
  "version": "0.9.1",
  "respondent": "Various Stakeholders at IRCC",
  "qa_section_text": "Section 3.1: Impact Questions and Answers\nRisk Profile\n1. Is the project within an area of intense public scrutiny (e.g. because of privacy concerns) and/\nor frequent litigation?\nYes [ Points: +3 ]\n2. Are clients in this line of business particularly vulnerable?\nNo [ Points: +0 ]\n3. Are stakes of the decisions very high?\nYes [ Points: +4 ]\n4. Will this project have major impacts on staff, either in terms of their numbers or their roles?\nYes [ Points: +3 ]\nProject Authority\n5. Will you require new policy authority for this project?\nNo [ Points: +0 ]\nAbout the Algorithm\n6. The algorithm used will be a (trade) secret\nNo [ Points: +0 ]\n7. The algorithmic process will be difficult to interpret or to explain\nNo [ Points: +0 ]\nAbout the Decision\n8. Does the decision pertain to any of the categories below (check all that apply):\nOther (please specify) [ Points: +1 ]\n9. Please describe\nImmigration services\nImpact Assessment\n10. Will the system only be used to assist a decision-maker?\nNo [ Points: +0 ]\n11. Will the system be replacing a decision that would otherwise be made by a human?\nYes [ Points: +3 ]\n12. Will the system be replacing human decisions that require judgement or discretion?\nYes [ Points: +4 ]\n13. Please describe the decision(s) that will be automated\nThe system will automate the approval of the eligibility of some Sponsors and\nPrincipal Applicants for in-Canada Spousal and Common-law Permanent\nResident applications. For applications where the positive eligibility\ndetermination is automated by the model, the model determines only that an\napplicant is eligible, before the application is sent to an officer to screen for\nadmissibility. Even in cases where the model approves the eligibility, officers\ncontinue to make the final decision on each application.\n14. Is the system used by a different part of the organization than the ones who developed it?\nYes [ Points: +4 ]\n15. Are the impacts resulting from the decision reversible?\nReversible [ Points: +1 ]\n16. How long will impacts from the decision last?\nMost impacts are perpetual [ Points: +4 ]\n17. Please describe why the impacts resulting from the decision are as per selected option\nabove.\nThe algorithm will be making a positive eligibility assessment that will only\nrarely be overturned.\n18. The impacts that the decision will have on the rights or freedoms of individuals will likely be:\nLittle to no impact [ Points: +1 ]\n19. Please describe why the impacts resulting from the decision are (as per selected option\nabove).\nThe model assesses data elements in applications submitted to IRCC to\ntriage applications and to automate certain positive eligibility determinations.\nThe model is expected to have little to no impact on the rights and freedoms\nof individuals as it will solely be used to triage applications and to automate\ncertain positive eligibility determinations. The model rules also only use data\nelements with a clear link to legislative and regulatory requirements. The\nmodel never refuses applications nor does it recommend refusals. All refusals\ncontinue to be done by humans as per the current practice. All applications for\nwhich eligibility cannot be approved by the model will receive a full\nindividualized assessment by officers in accordance with standard practice,\nincluding an officer determining eligibility and screening for admissibility.\nOfficers continue to make the final decision on each application. For\napplications where the positive eligibility determination is automated by the\nmodel, the model determines only that an applicant is eligible, before the\napplication is sent to an officer to screen for admissibility. Even in cases\nwhere the model approves the eligibility, officers continue to make the final\ndecision on each application.\nThe impact of the triage performed by the model on decision-making officers\nis limited because officers will not be aware of the rules used by the model for\nits triage or automated positive eligibility determinations, nor will they receive\nany information about the analysis that was performed by the model. Further,\nthe model does not produce a recommendation to officers. Each assessment\nby an officer of an application will be individualized. Model rules were\nreviewed by experienced officers, legal, policy, data science, and privacy\nexperts, as well as senior decision-makers to ensure they were logical,\nunderstandable and aligned with established eligibility criteria. Regular\nmonitoring and quality assurance measures will also help make sure the\nmodel continues to perform as intended and that any unforeseen negative\nimpacts such as bias or discrimination can be identified early and mitigated.\n20. The impacts that the decision will have on the health and well-being of individuals will likely\nbe:\nLittle to no impact [ Points: +1 ]\n21. Please describe why the impacts resulting from the decision are (as per selected option\nabove)\nThe model is expected to have little to no negative impact on the health and\nwell-being of",
  "_full_text": "Algorithmic Impact Assessment Results\nVersion: 0.9.1\nProject Details\n1. Name of Respondent\nVarious Stakeholders at IRCC\n2. Department\nCitizenship and Immigration (Department of)\n3. Branch\nVarious Branches at IRCC\n4. Project Title\nSpouse or Common-Law Partner in Canada Advanced Analytics\n5. Departmental Program (from Department Results Framework)\nFamily Reunification\n6. Project Phase\nImplementation [ Points: 0 ]\n7. Please provide a project description:\nThis project seeks to streamline the eligibility assessment for both the\nSponsor and Principal Applicant of Spouse or Common-law Partner in Canada\napplications.\nBusiness Driver / Positive Impact\n8. What is motivating your team to introduce automation into this decision-making process?\n(Check all that apply)\nExisting backlog of work or cases\nOther (please specify)\n9. Please describe\nFacilitate expedited processing to assist IRCC to meet processing target.\nAbout The System\n10. Please check which of the following capabilities apply to your system.\nProcess optimization and workflow automation: Analyzing large data sets to\nidentify and anomalies, cluster patterns, predict outcomes or ways to\noptimize; and automate specific workflows\nSection 1: Impact Level : 2\nCurrent Score: 43\nRaw Impact Score: 43\nMitigation Score: 31\nSection 2: Requirements Specific to Impact Level 2\nPeer Review\nAt least one of:\nQualified expert from a federal, provincial, territorial or municipal government institution.\nQualified members of faculty of a post-secondary institution.\nQualified researchers from a relevant non-governmental organization.\nContracted third-party vendor with a related specialization.\nPublishing specifications of the Automated Decision System in a peer-reviewed journal.\nA data and automation advisory board specified by Treasury Board Secretariat.\nNotice\nPlain language notice posted through all service delivery channels in use (Internet, in person,\nmail or telephone).\nHuman-in-the-loop for decisions\nDecisions may be rendered without direct human involvement.\nExplanation Requirement\nIn addition to any applicable legal requirement, ensuring that a meaningful explanation is\nprovided with any decision that resulted in the denial of a benefit, a service, or other regulatory\naction.\nTraining\nDocumentation on the design and functionality of the system.\nContingency Planning\nNone\nApproval for the system to operate\nNone\nOther Requirements\nThe Directive on Automated Decision-Making also includes other requirements that must be met\nfor all impact levels.\nLink to the Directive on Automated Decision-Making\nContact your institution's ATIP office to discuss the requirement for a Privacy Impact\nAssessment as per the Directive on Privacy Impact Assessment.\nSection 3: Questions and Answers\nSection 3.1: Impact Questions and Answers\nRisk Profile\n1. Is the project within an area of intense public scrutiny (e.g. because of privacy concerns) and/\nor frequent litigation?\nYes [ Points: +3 ]\n2. Are clients in this line of business particularly vulnerable?\nNo [ Points: +0 ]\n3. Are stakes of the decisions very high?\nYes [ Points: +4 ]\n4. Will this project have major impacts on staff, either in terms of their numbers or their roles?\nYes [ Points: +3 ]\nProject Authority\n5. Will you require new policy authority for this project?\nNo [ Points: +0 ]\nAbout the Algorithm\n6. The algorithm used will be a (trade) secret\nNo [ Points: +0 ]\n7. The algorithmic process will be difficult to interpret or to explain\nNo [ Points: +0 ]\nAbout the Decision\n8. Does the decision pertain to any of the categories below (check all that apply):\nOther (please specify) [ Points: +1 ]\n9. Please describe\nImmigration services\nImpact Assessment\n10. Will the system only be used to assist a decision-maker?\nNo [ Points: +0 ]\n11. Will the system be replacing a decision that would otherwise be made by a human?\nYes [ Points: +3 ]\n12. Will the system be replacing human decisions that require judgement or discretion?\nYes [ Points: +4 ]\n13. Please describe the decision(s) that will be automated\nThe system will automate the approval of the eligibility of some Sponsors and\nPrincipal Applicants for in-Canada Spousal and Common-law Permanent\nResident applications. For applications where the positive eligibility\ndetermination is automated by the model, the model determines only that an\napplicant is eligible, before the application is sent to an officer to screen for\nadmissibility. Even in cases where the model approves the eligibility, officers\ncontinue to make the final decision on each application.\n14. Is the system used by a different part of the organization than the ones who developed it?\nYes [ Points: +4 ]\n15. Are the impacts resulting from the decision reversible?\nReversible [ Points: +1 ]\n16. How long will impacts from the decision last?\nMost impacts are perpetual [ Points: +4 ]\n17. Please describe why the impacts resulting from the decision are as per selected option\nabove.\nThe algorithm will be making a positive eligibility assessment that will only\nrarely be overturned.\n18. The impacts that the decision will have on the rights or freedoms of individuals will likely be:\nLittle to no impact [ Points: +1 ]\n19. Please describe why the impacts resulting from the decision are (as per selected option\nabove).\nThe model assesses data elements in applications submitted to IRCC to\ntriage applications and to automate certain positive eligibility determinations.\nThe model is expected to have little to no impact on the rights and freedoms\nof individuals as it will solely be used to triage applications and to automate\ncertain positive eligibility determinations. The model rules also only use data\nelements with a clear link to legislative and regulatory requirements. The\nmodel never refuses applications nor does it recommend refusals. All refusals\ncontinue to be done by humans as per the current practice. All applications for\nwhich eligibility cannot be approved by the model will receive a full\nindividualized assessment by officers in accordance with standard practice,\nincluding an officer determining eligibility and screening for admissibility.\nOfficers continue to make the final decision on each application. For\napplications where the positive eligibility determination is automated by the\nmodel, the model determines only that an applicant is eligible, before the\napplication is sent to an officer to screen for admissibility. Even in cases\nwhere the model approves the eligibility, officers continue to make the final\ndecision on each application.\nThe impact of the triage performed by the model on decision-making officers\nis limited because officers will not be aware of the rules used by the model for\nits triage or automated positive eligibility determinations, nor will they receive\nany information about the analysis that was performed by the model. Further,\nthe model does not produce a recommendation to officers. Each assessment\nby an officer of an application will be individualized. Model rules were\nreviewed by experienced officers, legal, policy, data science, and privacy\nexperts, as well as senior decision-makers to ensure they were logical,\nunderstandable and aligned with established eligibility criteria. Regular\nmonitoring and quality assurance measures will also help make sure the\nmodel continues to perform as intended and that any unforeseen negative\nimpacts such as bias or discrimination can be identified early and mitigated.\n20. The impacts that the decision will have on the health and well-being of individuals will likely\nbe:\nLittle to no impact [ Points: +1 ]\n21. Please describe why the impacts resulting from the decision are (as per selected option\nabove)\nThe model is expected to have little to no negative impact on the health and\nwell-being of individuals as it will solely be used to triage applications and to\nautomate certain positive eligibility determinations.\n22. The impacts that the decision will have on the economic interests of individuals will likely\nbe:\nLittle to no impact [ Points: +1 ]\n23. Please describe why the impacts resulting from the decision are (as per selected option\nabove)\nThe model is expected to have little to no negative impact on the economic\ninterests of individuals as it will solely be used to triage applications and to\nautomate certain positive eligibility determinations.\n24. The impacts that the decision will have on the ongoing sustainability of an environmental\necosystem, will likely be:\nLittle to no impact [ Points: +1 ]\n25. Please describe why the impacts resulting from the decision are (as per selected option\nabove)\nThe model is expected to have little to no negative impact on the environment\nas it will solely be used to triage applications and to automate certain positive\neligibility determinations.\nAbout the Data - A. Data Source\n26. Will the Automated Decision System use personal information as input data?\nYes [ Points: +4 ]\n27. Have you verified that the use of personal information is limited to only what is directly\nrelated to delivering a program or service?\nYes [ Points: +0 ]\n28. Is the personal information of individuals being used in a decision-making process that\ndirectly affects those individuals?\nYes [ Points: +2 ]\n29. Have you verified if the system is using personal information in a way that is consistent\nwith: (a) the current Personal Information Banks (PIBs) and Privacy Impact Assessments (PIAs)\nof your programs or (b) planned or implemented modifications to the PIBs or PIAs that take new\nuses and processes into account?\nYes [ Points: +0 ]\n30. What is the highest security classification of the input data used by the system? (Select one)\nProtected B / Protected C [ Points: +3 ]\n31. Who controls the data?\nFederal government [ Points: +1 ]\n32. Will the system use data from multiple different sources?\nNo [ Points: +0 ]\n33. Will the system require input data from an Internet- or telephony-connected device? (e.g.\nInternet of Things, sensor)\nNo [ Points: +0 ]\n34. Will the system interface with other IT systems?\nNo [ Points: +0 ]\n35. Who collected the data used for training the system?\nYour institution [ Points: +1 ]\n36. Who collected the input data used by the system?\nYour institution [ Points: +1 ]\nAbout the Data - B. Type of Data\n37. Will the system require the analysis of unstructured data to render a recommendation or a\ndecision?\nNo [ Points: 0 ]\nSection 3.2: Mitigation Questions and Answers\nConsultations\n1. Internal Stakeholders (Strategic policy and planning, Data Governance, Program Policy, etc.)\nYes [ Points: +1 ]\n2. Which Internal Stakeholders have you engaged?\nStrategic Policy and Planning\nData Governance\nProgram Policy\nLegal Services\nAccess to Information and Privacy Office\nCommunications\nClient Experience / Client Relationship Management\nOther (describe)\n3. Please describe\nIntegrity Risk Management, IT Security, Centralized Network, GBA+, Change\nManagement, etc.\n4. External Stakeholders (Civil Society, Academia, Industry, etc.)\nYes [ Points: +1 ]\n5. Which External Stakeholders have you engaged?\nOffice of the Privacy Commissioner\nDe-Risking and Mitigation Measures - Data Quality\n6. Do you have documented processes in place to test datasets against biases and other\nunexpected outcomes? This could include experience in applying frameworks, methods,\nguidelines or other assessment tools.\nYes [ Points: +2 ]\n7. Is this information publicly available?\nNo [ Points: +0 ]\n8. Have you developed a process to document how data quality issues were resolved during the\ndesign process?\nYes [ Points: +1 ]\n9. Is this information publicly available?\nNo [ Points: +0 ]\n10. Have you undertaken a Gender Based Analysis Plus of the data?\nYes [ Points: +1 ]\n11. Is this information publicly available?\nNo [ Points: +0 ]\n12. Have you assigned accountability in your institution for the design, development,\nmaintenance, and improvement of the system?\nYes [ Points: +2 ]\n13. Do you have a documented process to manage the risk that outdated or unreliable data is\nused to make an automated decision?\nNo [ Points: +0 ]\n14. Is this information publicly available?\nNo [ Points: +0 ]\n15. Is the data used for this system posted on the Open Government Portal?\nNo [ Points: +0 ]\nDe-Risking and Mitigation Measures - Procedural\nFairness\n16. Does the audit trail identify the authority or delegated authority identified in legislation?\nYes [ Points: +1 ]\n17. Does the system provide an audit trail that records all the recommendations or decisions\nmade by the system?\nYes [ Points: +2 ]\n18. Are all key decision points identifiable in the audit trail?\nYes [ Points: +2 ]\n19. Are all key decision points within the automated system's logic linked to the relevant\nlegislation, policy or procedures?\nYes [ Points: +1 ]\n20. Do you maintain a current and up to date log detailing all of the changes made to the model\nand the system?\nYes [ Points: +2 ]\n21. Does the system's audit trail indicate all of the decision points made by the system?\nYes [ Points: +1 ]\n22. Can the audit trail generated by the system be used to help generate a notification of the\ndecision (including a statement of reasons or other notifications) where required?\nYes [ Points: +1 ]\n23. Does the audit trail identify precisely which version of the system was used for each\ndecision it supports?\nYes [ Points: +2 ]\n24. Does the audit trail show who an authorized decision-maker is?\nYes [ Points: +1 ]\n25. Is the system able to produce reasons for its decisions or recommendations when required?\nYes [ Points: +2 ]\n26. Is there a process in place to grant, monitor, and revoke access permission to the system?\nYes [ Points: +1 ]\n27. Is there a mechanism to capture feedback by users of the system?\nYes [ Points: +1 ]\n28. Is there a recourse process established for clients that wish to challenge the decision?\nYes [ Points: +2 ]\n29. Does the system enable human override of system decisions?\nYes [ Points: +2 ]\n30. Is there a process in place to log the instances when overrides were performed?\nYes [ Points: +1 ]\n31. Does the system's audit trail include change control processes to record modifications to the\nsystem's operation or performance?\nNo [ Points: +0 ]\n32. Have you prepared a concept case to the Government of Canada Enterprise Architecture\nReview Board?\nNo [ Points: +0 ]\nDe-Risking and Mitigation Measures - Privacy\n33. If your system involves the use of personal information, have you undertaken a Privacy\nImpact Assessment, or updated an existing one?\nNo [ Points: +0 ]\n34. Have you designed and built security and privacy into your systems from the concept stage\nof the project?\nYes [ Points: +1 ]\n35. Is the information used within a closed system (i.e. no connections to the Internet, Intranet\nor any other system)?\nNo [ Points: +0 ]\n36. If the sharing of personal information is involved, has an agreement or arrangement with\nappropriate safeguards been established?\nNo [ Points: +0 ]",
  "dataset_id": "d41f9ec2-bf01-4b2a-bd8d-1b3a8424f534",
  "source_file": "algorithmic-impact-assessment-spouse-or-common-law-partner-in-canada-advanced-analytics-english.pdf"
}